{
  "anuppuccin-theme-settings-extended@@anp-theme-ext-dark": true,
  "anuppuccin-theme-settings-extended@@anp-theme-ext-light": false,
  "anuppuccin-theme-settings-extended@@anp-theme-ext-amoled": false,
  "anuppuccin-theme-settings@@anp-codeblock-numbers": false,
  "anuppuccin-theme-settings@@anp-codeblock-wrap-hl-preview": "none",
  "anuppuccin-theme-settings-extended@@catppuccin-theme-dark-extended": "ctp-atom-dark",
  "Blue-Topaz-Codebox-Highlight@@code-box-style-option": "codebox-default-style",
  "blue-topaz-theme@@color-scheme-options": "null",
  "Blue-Topaz-Codebox-Highlight@@code-theme-selection": "code-theme-material-palenight",
  "minimal-advanced@@hide-markdown": false,
  "minimal-style@@h3-variant": "normal",
  "minimal-style@@h3-l": false,
  "minimal-style@@trim-cols": true,
  "minimal-style@@dataview-inline-lists": false,
  "minimal-style@@icon-muted": 0.5,
  "minimal-style@@window-title-off": false,
  "minimal-style@@code-function@@dark": "#519EEB",
  "anuppuccin-theme-settings@@anp-alt-rainbow-style": "anp-simple-rainbow-color-toggle",
  "anuppuccin-theme-settings@@anp-rainbow-file-toggle": false,
  "anuppuccin-theme-settings@@anp-full-rainbow-text-color-toggle-light": false,
  "anuppuccin-theme-settings@@anp-simple-rainbow-title-toggle": true,
  "anuppuccin-theme-settings@@anp-simple-rainbow-collapse-icon-toggle": true,
  "anuppuccin-theme-settings@@anp-simple-rainbow-indentation-toggle": true,
  "anuppuccin-theme-settings@@anp-simple-rainbow-icon-toggle": false,
  "anuppuccin-theme-settings@@anp-rainbow-subfolder-color-toggle": false,
  "anuppuccin-theme-settings@@anp-custom-checkboxes": false,
  "anuppuccin-theme-settings@@anp-header-color-toggle": true,
  "anuppuccin-theme-settings@@anp-header-margin-toggle": false,
  "anuppuccin-theme-settings@@anp-header-divider-color-toggle": false,
  "anuppuccin-theme-settings@@h1-size": 1.3,
  "anuppuccin-theme-settings@@h2-size": 1.25,
  "anuppuccin-theme-settings@@h3-size": 1.2,
  "anuppuccin-theme-settings@@anp-h2-color-custom": "anp-h2-blue",
  "anuppuccin-theme-settings@@anp-h3-color-custom": "anp-h3-peach",
  "anuppuccin-theme-settings@@h2-line-height": 1.25,
  "anuppuccin-theme-settings@@h3-line-height": 1.2,
  "anuppuccin-theme-settings@@h4-size": 1.15,
  "anuppuccin-theme-settings@@h4-line-height": 1.1,
  "anuppuccin-theme-settings@@h1-line-height": 1.25,
  "anuppuccin-theme-settings@@anp-h4-color-custom": "anp-h4-sapphire",
  "anuppuccin-theme-settings@@anp-h4-divider": false,
  "anuppuccin-theme-settings@@anp-h2-divider": true,
  "anuppuccin-theme-settings@@anp-canvas-dark-bg": false,
  "anuppuccin-theme-settings@@anp-colorful-frame": false,
  "anuppuccin-theme-settings@@anp-colorful-frame-icon-toggle-light": false,
  "anuppuccin-theme-settings@@anp-colorful-frame-icon-toggle-dark": false,
  "anuppuccin-theme-settings@@anp-layout-select": "none",
  "anuppuccin-theme-settings@@anuppuccin-theme-dark": "ctp-mocha-old",
  "anuppuccin-theme-settings@@anp-code-bg-color@@dark": "#1E2127",
  "anuppuccin-theme-settings@@callout-title-opacity": 0.1,
  "anuppuccin-theme-settings@@anp-codeblock-wrap-edit": "none",
  "anuppuccin-theme-settings@@anp-codeblock-wrap-preview": "none",
  "minimal-style@@callouts-style": "callouts-default",
  "minimal-style@@ribbon-style": "ribbon-bottom-left-hover",
  "minimal-style@@row-lines": false,
  "minimal-style@@minimal-unstyled-tags": false,
  "minimal-style@@tag-radius": "4px",
  "minimal-style@@tag-border-width": "2px",
  "minimal-style@@file-header-visibility": "minimal-tab-title-visible",
  "minimal-style@@file-header-font-weight": 400,
  "minimal-style@@file-header-justify": "left",
  "minimal-style@@h2-variant": "normal",
  "minimal-style@@h2-color@@dark": "#5682E4",
  "minimal-style@@h4-size": "1em",
  "minimal-style@@h3-style": "normal",
  "minimal-style@@h3-color@@dark": "#8AB97C",
  "minimal-style@@h4-color@@dark": "#539DE9",
  "minimal-style@@minimal-code-scroll": false,
  "minimal-style@@code-important@@dark": "#FFFFFF",
  "minimal-style@@code-keyword@@dark": "#B75DD4"
}